tanimachi/__init__.py
tanimachi/wappalyzer.py
tanimachi/schemas/__init__.py
tanimachi/schemas/api_model.py
tanimachi/schemas/har.py
tanimachi/schemas/mixins.py
tanimachi/schemas/wappalyzer.py
tanimachi-0.0.6.dist-info/METADATA
tanimachi-0.0.6.dist-info/WHEEL
tanimachi-0.0.6.dist-info/licenses/LICENSE
tanimachi-0.0.6.dist-info/RECORD
