Metadata-Version: 2.3
Name: tanimachi
Version: 0.0.6
Summary: An opinionated Wappalyzer compatible fingerprint engine works along with HAR
License-File: LICENSE
Requires-Python: >=3.10
Requires-Dist: loguru~=0.7
Requires-Dist: pydantic~=2.9
Requires-Dist: returns~=0.23
Requires-Dist: selectolax~=0.3
